torrentmirror/__init__.py
torrentmirror-2.0.3.dist-info/entry_points.txt
torrentmirror-2.0.3.dist-info/WHEEL
torrentmirror-2.0.3.dist-info/METADATA
torrentmirror-2.0.3.dist-info/RECORD
