Metadata-Version: 2.1
Name: torrentmirror
Version: 2.0.3
Summary: TorrentMirror API and CLI interface
Author: David Francos
Author-email: opensource@davidfrancos.net
Requires-Python: >=3.8,<4.0
Classifier: Programming Language :: Python :: 3
Classifier: Programming Language :: Python :: 3.8
Classifier: Programming Language :: Python :: 3.9
Requires-Dist: cleo (>=0.8.1,<0.9.0)
Requires-Dist: docopt (>=0.6.2,<0.7.0)
Requires-Dist: pygogo (>=0.13.2,<0.14.0)
Requires-Dist: robobrowser (>=0.5.3,<0.6.0)
Requires-Dist: tabulate (>=0.8.7,<0.9.0)
Requires-Dist: xdg (>=5.0.1,<6.0.0)
Requires-Dist: yapf (>=0.30.0,<0.31.0)
